{"scenarios_Balance_Check":{"name":"Balance Check","input":{"office":"","department":"","bic":"","country":"","currency":"","mop":""},"values":{"1":{"type":"script","name":"BI invocation Point","key":"users","description":"BI is performed after Fees and FX: Fees > FX > BI","action":"","scope":"Phase 1","status":""},"2":{"type":"script","name":"BI invocation Point","key":"users","description":"BI is performed on the debit side. No balance inquiry on the credit side.","action":"","scope":"Phase 1","status":""},"3":{"type":"script","name":"BI invocation Point","key":"users","description":"BI is performed on the debit side. No balance inquiry on the credit side.","action":"","scope":"Phase 1","status":""},"4":{"type":"script","name":"Bypass BI","key":"users","description":"Balance Inquiry must not be invoked upon the Posting 1st step.","action":"","scope":"Phase 1","status":""},"5":{"type":"script","name":"Inteface Selection","key":"users","description":"The relevant BI interface is selected","action":"","scope":"Phase 1","status":""},"6":{"type":"script","name":"BI Request content","key":"users","description":"GPP is required to send Base rate and Spot rate as part of the Balance Inquiry ","action":"","scope":"Phase 1","status":""},"7":{"type":"script","name":"BI Request / Response content","key":"users","description":"Request and Response layout should be the same as for Delivery 1.","action":"","scope":"Phase 1","status":""},"8":{"type":"script","name":"Interface Wait Behavior","key":"users","description":"Message must wait for a response in order to proceed with the flow","action":"","scope":"Phase 1","status":""},"9":{"type":"script","name":"Interface Inactive behavior","key":"users","description":"The interface is Inactive For FILE Source:  Request is not created (except 990), stop the flow, and put the message in status BI_STOP. When the interface is active again, create the request, send it and continue with the flow. Source <> FILE: Request is not created (except 990), stop the flow, and put the message in status Rejected.","action":"","scope":"Phase 1","status":""},"10":{"type":"script","name":"Response Handling","key":"users","description":"For FILE Source:  Stop the flow, and put the message in status BI_STOP. When the interface is active again, create the request, send it and continue with the flow. Source <> FILE: Stop the flow and put the message in status Rejected.","action":"","scope":"Phase 1","status":""},"11":{"type":"script","name":"Response Handling","key":"users","description":"Flow continues.","action":"","scope":"Phase 1","status":""},"12":{"type":"script","name":"Response Handling","key":"users","action":"","scope":"Phase 1","status":""},"13":{"type":"script","name":"NSF","key":"users","description":"Re-tries will be done in a certain frequency.","action":"","scope":"Phase 1","status":""}}}}